README.md
setup.cfg
setup.py
wundercell/__init__.py
wundercell/dataloader.py
wundercell/inputs.py
wundercell.egg-info/PKG-INFO
wundercell.egg-info/SOURCES.txt
wundercell.egg-info/dependency_links.txt
wundercell.egg-info/requires.txt
wundercell.egg-info/top_level.txt