Metadata-Version: 1.1
Name: wundercell
Version: 0.0.1
Summary: Wundercell package to extend the notebook environment
Home-page: https://wundercell.com
Author: hackwagon
Author-email: hello@hackwagon.com
License: UNKNOWN
Platform: UNKNOWN
Classifier: Programming Language :: Python :: 3
Classifier: License :: OSI Approved :: MIT License
Classifier: Operating System :: OS Independent
